README.txt
setup.cfg
setup.py
Django_Integrator.egg-info/PKG-INFO
Django_Integrator.egg-info/SOURCES.txt
Django_Integrator.egg-info/dependency_links.txt
Django_Integrator.egg-info/entry_points.txt
Django_Integrator.egg-info/requires.txt
Django_Integrator.egg-info/top_level.txt
django_integrator/__init__.py
django_integrator/main.py
django_integrator_script/__init__.py
django_integrator_script/create.py
django_integrator_script/make_application.py
django_integrator_script/templates/README.txt
django_integrator_script/templates/admin_py.txt
django_integrator_script/templates/devset_py.txt
django_integrator_script/templates/info_py.txt
django_integrator_script/templates/init_py.txt
django_integrator_script/templates/license_template.txt
django_integrator_script/templates/models_py.txt
django_integrator_script/templates/sanitize_py.txt
django_integrator_script/templates/settings_py.txt
django_integrator_script/templates/setup_cfg.txt
django_integrator_script/templates/setup_py.txt
django_integrator_script/templates/signals_py.txt
django_integrator_script/templates/urls_py.txt
django_integrator_script/templates/views_py.txt