Metadata-Version: 1.1
Name: Django-Integrator
Version: 1.0.1.2
Summary: Create and use django-integrator compliant applications.
Home-page: https://bitbucket.org/hellwig/Django-Integrator/
Author: Martin P. Hellwig
Author-email: martin.hellwig@gmail.com
License: BSD
Download-URL: https://bitbucket.org/hellwig/Django-Integrator/get/7c2f1744f7575ea852f8ad52ca8259b97fa1bab1.zip
Keywords: django
Platform: UNKNOWN
Classifier: Programming Language :: Python :: 3
